{
  "nombre": "4ta Caballeros",
  "grupos": [
    {
      "nombre": "Grupo A",
      "equipos": [
        {
          "nombre": "Lucas Ojeda/Ivan Gallardo",
          "PJ": 0,
          "PG": 0,
          "SG": 0,
          "SP": 0,
          "GF": 0,
          "GC": 0
        },
        {
          "nombre": "Nicolas Gonzalez",
          "PJ": 0,
          "PG": 0,
          "SG": 0,
          "SP": 0,
          "GF": 0,
          "GC": 0
        },
        {
          "nombre": "Tiago Andrade/Franco Moreno",
          "PJ": 0,
          "PG": 0,
          "SG": 0,
          "SP": 0,
          "GF": 0,
          "GC": 0
        }
        
      ],
      "partidos": [
        {
          "fecha": "Miercoles 21:00 hs",
          "equipo1": "Lucas Ojeda/Ivan Gallardo",
          "equipo2": "Nicolas Gonzalez",
          "resultado": "",
          "games":""
        },
        {
          "fecha": "Jueves 21:00 hs",
          "equipo1": "Lucas Ojeda/Ivan Gallardo",
          "equipo2": "Tiago Andrade/Franco Moreno",
          "resultado": "",
          "games":""
        },
        {
          "fecha": "Sabado 14:40 hs",
          "equipo1": "Tiago Andrade/Franco Moreno",
          "equipo2": "Nicolas Gonzalez",
          "resultado": "",
          "games":""
        }
        
      ]
    },
   {
      "nombre": "Grupo B",
      "equipos": [
        {
          "nombre": "Joaquin Servian/Yannick Sanchez",
          "PJ": 0,
          "PG": 0,
          "SG": 0,
          "SP": 0,
          "GF": 0,
          "GC": 0
        },
        {
          "nombre": "Mauro Pucheta/Emmanuel Barrios",
          "PJ": 0,
          "PG": 0,
          "SG": 0,
          "SP": 0,
          "GF": 0,
          "GC": 0
        },
        {
          "nombre": "Julio Andrade/Cesar Andrade",
          "PJ": 0,
          "PG": 0,
          "SG": 0,
          "SP": 0,
          "GF": 0,
          "GC": 0
        }
        
      ],
      "partidos": [
        {
          "fecha": "Jueves 22:10 hs",
          "equipo1": "Mauro Pucheta/Emmanuel Barrios",
          "equipo2": "Julio Andrade/Cesar Andrade",
          "resultado": "",
          "games":""
        },
        {
          "fecha": "Sabado 13:30 hs",
          "equipo1": "Joaquin Servian/Yannick Sanchez",
          "equipo2": "Julio Andrade/Cesar Andrade",
          "resultado": "",
          "games":""
        },
        {
          "fecha": "Sabado 17:00 hs",
          "equipo1": "Joaquin Servian/Yannick Sanchez",
          "equipo2": "Mauro Pucheta/Emmanuel Barrios",
          "resultado": "",
          "games":""
        }
        
      ]
    },
    
    {
      "nombre": "Grupo C",
      "equipos": [
        {
          "nombre": "Jose Villarreal/Martin Ormaza",
          "PJ": 0,
          "PG": 0,
          "SG": 0,
          "SP": 0,
          "GF": 0,
          "GC": 0
        },
        {
          "nombre": "Diego Mancini/Raul Maldonado",
          "PJ": 0,
          "PG": 0,
          "SG": 0,
          "SP": 0,
          "GF": 0,
          "GC": 0
        },
        {
          "nombre": "Jorge Carbajal/Ignacio Carbajal",
          "PJ": 0,
          "PG": 0,
          "SG": 0,
          "SP": 0,
          "GF": 0,
          "GC": 0
        },
        {
          "nombre": "Gabriel Muller/Claudio Escobar",
          "PJ": 0,
          "PG": 0,
          "SG": 0,
          "SP": 0,
          "GF": 0,
          "GC": 0
        }
        
      ],
      "partidos": [
        {
          "fecha": "Viernes 19:50 hs",
          "equipo1": "Jose Villarreal/Martin Ormaza",
          "equipo2": "Diego Mancini/Raul Maldonado",
          "resultado": "",
          "games":""
        },
        {
          "fecha": "Miercoles 19:50 hs",
          "equipo1": "Jorge Carbajal/Ignacio Carbajal",
          "equipo2": "Gabriel Muller/Claudio Escobar",
          "resultado": "",
          "games":""
        },
        {
          "fecha": "Sabado :00 hs",
          "equipo1": "Ganador Partido 1",
          "equipo2": "Perdedor Partido 2",
          "resultado": "",
          "games":"A definir"
        },
        {
          "fecha": "Sabado :00 hs",
          "equipo1": "Ganador Partido 2",
          "equipo2": "Perdedor Partido 1",
          "resultado": "",
          "games":"A definir"
        }
      ]
    }
  ],
  "eliminatorias": {
    
    "cuartos": [
      {
         "equipo1": "2do B",
          "equipo2": "2do C",
          "fecha": "Domingo",
          "resultado": "A definir",
          "games":""
      },
      {
          "equipo1": "1ro C",
          "equipo2": "2do A",
          "fecha": "Domingo",
          "resultado": "A definir",
          "games":""
      }
    ],
    "semis": [
      {
         "equipo1": "1ro A",
          "equipo2": "Ganador P1",
          "fecha": "Domingo",
          "resultado": "A definir",
          "games":""
      },
      {
         "equipo1": "Ganador P2",
          "equipo2": "1ro B",
          "fecha": "Domingo",
          "resultado": "A definir",
          "games":""
      }
    ],
    "final": {
       "equipo1": "Ganador P5",
          "equipo2": "Ganador P6",
          "fecha": "Domingo",
          "resultado": "A definir",
          "games":""
    }
  }
}